{
	"numberOfSqures": "8",
	"playerInfo": {
		"star": "0",
		"name": "Mehdi",
		"id": "maryam",
		"currentposition": "13"
	},
	"ladders": {
		"Sucess": {
			"x": "5",
			"y": "12"
		},
		"Up": {
			"x": "10",
			"y": "52"
		},
		"Win": {
			"x": "36",
			"y": "50"
		},
		"Hope": {
			"x": "52",
			"y": "20"
		}
	},
	"sankes": {
		"Bova": {
			"x": "61",
			"y": "43"
		},
		"Kobra": {
			"x": "34",
			"y": "20"
		},
		"Python": {
			"x": "11",
			"y": "8"
		},
		"Piton": {
			"x": "52",
			"y": "8"
		}
		}
}